MeliAPIClient/__init__.py
MeliAPIClient/actions.py
MeliAPIClient/bill.py
MeliAPIClient/order.py
MeliAPIClient/session.py
MeliAPIClient/ship.py
MeliAPIClient-0.0.1.dist-info/METADATA
MeliAPIClient-0.0.1.dist-info/WHEEL
MeliAPIClient-0.0.1.dist-info/top_level.txt
MeliAPIClient-0.0.1.dist-info/RECORD
