Metadata-Version: 2.1
Name: MeliAPIClient
Version: 0.0.1
Summary: Este paquete nos permite consumir el API de mercado libre
Home-page: https://github.com/andresroh/MeliAPIClient
Author: Camilo Andrés Rodríguez Higuera
Author-email: hola@camilordz.com
License: MIT
Keywords: python,mercado libre,mercadolibre.com
Classifier: Development Status :: 3 - Alpha
Classifier: Intended Audience :: Developers
Classifier: Topic :: Software Development :: Build Tools
Classifier: License :: OSI Approved :: MIT License
Classifier: Programming Language :: Python :: 3
Requires-Dist: requests
